bruce/__init__.py
bruce/builder/__init__.py
bruce/builder/builder.py
bruce/cache/__init__.py
bruce/cache/cache.py
bruce/cache/fingerprinting.py
bruce/cli/__init__.py
bruce/cli/cli.py
bruce/exceptions/__init__.py
bruce/parser/__init__.py
bruce/parser/ini.py
bruce/parser/parser.py
bruce/parser/toml_.py
bruce/task/__init__.py
bruce/task/task.py
bruce/toposort/__init__.py
bruce/toposort/toposort.py
bruce/watchable/__init__.py
bruce/watchable/watchable.py
bruce_bld-0.0.10.dist-info/LICENSE
bruce_bld-0.0.10.dist-info/METADATA
bruce_bld-0.0.10.dist-info/WHEEL
bruce_bld-0.0.10.dist-info/top_level.txt
bruce_bld-0.0.10.dist-info/RECORD
