Metadata-Version: 2.1
Name: bruce-bld
Version: 0.0.10
Summary: Small Command Executor
Home-page: UNKNOWN
Author: Mathieu Sabourin
Author-email: mathieu.c.sabourin@gmail.com
License: UNKNOWN
Platform: UNKNOWN
Provides-Extra: toml
Requires-Dist: toml ; extra == 'toml'
